lgt/common/python/aggregator_message.py
lgt/common/python/helpers.py
lgt/common/python/lgt_logging.py
lgt/common/python/discord_client/__init__.py
lgt/common/python/discord_client/discord_client.py
lgt/common/python/discord_client/methods.py
lgt/common/python/enums/__init__.py
lgt/common/python/enums/slack_errors.py
lgt/common/python/pubsub/.gitignore
lgt/common/python/pubsub/__init__.py
lgt/common/python/pubsub/command.py
lgt/common/python/pubsub/messages.py
lgt/common/python/pubsub/pubsubfactory.py
lgt/common/python/slack_client/.gitignore
lgt/common/python/slack_client/__init__.py
lgt/common/python/slack_client/methods.py
lgt/common/python/slack_client/slack_client.py
lgt/common/python/slack_client/web_client.py
leadguru_common-0.383.0.dist-info/METADATA
leadguru_common-0.383.0.dist-info/WHEEL
leadguru_common-0.383.0.dist-info/top_level.txt
leadguru_common-0.383.0.dist-info/RECORD
