Metadata-Version: 2.1
Name: leadguru-common
Version: 0.383.0
Summary: LGT common builds
Author-email: developer@leadguru.co
Requires-Dist: wheel
Requires-Dist: google-cloud-pubsub ==2.3.0
Requires-Dist: google-cloud-storage ==1.37.0
Requires-Dist: requests
Requires-Dist: aiohttp
Requires-Dist: websockets
Requires-Dist: loguru ==0.2.4
Requires-Dist: pydantic
Requires-Dist: leadguru-data >=0.60.0
Requires-Dist: pytz
